probarly/__init__.py
probarly/probarly.py
probarly-1.0.3.dist-info/LICENSE
probarly-1.0.3.dist-info/METADATA
probarly-1.0.3.dist-info/WHEEL
probarly-1.0.3.dist-info/top_level.txt
probarly-1.0.3.dist-info/RECORD
