Metadata-Version: 2.1
Name: probarly
Version: 1.0.3
Summary: Create beautiful, heavily customizable progress bars... probarly
Home-page: http://github.com/phil-gates/probarly
Author: Phil
Author-email: mateopw10@gmail.com
License: MIT
Platform: UNKNOWN
Classifier: Programming Language :: Python :: 3.7
License-File: LICENSE
